{"noiseKey":{"private":{"type":"Buffer","data":"UBo6maUqyhBUFWVqaAA6nIJiXY7UJ712lwB0//wMckk="},"public":{"type":"Buffer","data":"0+Si6Lv4jS6MzVSgr/g6Whhbte3yX+b+Z/P0MSfllmQ="}},"pairingEphemeralKeyPair":{"private":{"type":"Buffer","data":"SNMdFfdjqNJZl6qW59H3BukKCsu2Od2drav7GpLIcmg="},"public":{"type":"Buffer","data":"L2ps9E1NA5n2Hsy2GGjNxe3hJeI9nDTdzCN1IkXSXA0="}},"signedIdentityKey":{"private":{"type":"Buffer","data":"GJvid9/y8QROTQkKYzyznyOVGS/njVpfa1yZgP9zvXc="},"public":{"type":"Buffer","data":"D6zX1/QLGVGN14pypF+2Zefo4RzR14cOAacpo7kbNn4="}},"signedPreKey":{"keyPair":{"private":{"type":"Buffer","data":"gAY01Oxizca6pqtjcjeOvtdcSAzH8GM4TnfIwkT+Vl4="},"public":{"type":"Buffer","data":"05ho2EuM1CpQh0WBgz6BK3YWHRNoPf6JIUEWk8tweh0="}},"signature":{"type":"Buffer","data":"852kIq/OmS3wam7UJ+RcaQmeAaiPYVO8ZXuMxmHcEF85WCtewaO7SpyDGDjyh5T8IneU2pS3Mr50YpREL08cDw=="},"keyId":1},"registrationId":153,"advSecretKey":"OXova4tyr20NHFMzZTMx2QPauecbMCGUPRJf9Hv20dw=","processedHistoryMessages":[{"key":{"remoteJid":"2349122876837@s.whatsapp.net","fromMe":true,"id":"A5FA337844BFE887972AE53D4B2B0854","participant":"","addressingMode":"pn"},"messageTimestamp":1782012536},{"key":{"remoteJid":"2349122876837@s.whatsapp.net","fromMe":true,"id":"A5B5E3C149A198D1B04592775AE6E09F","participant":"","addressingMode":"pn"},"messageTimestamp":1782012537},{"key":{"remoteJid":"2349122876837@s.whatsapp.net","fromMe":true,"id":"A5C5C0833D89C697BEEDD97434AF2A77","participant":"","addressingMode":"pn"},"messageTimestamp":1782012538},{"key":{"remoteJid":"2349122876837@s.whatsapp.net","fromMe":true,"id":"A54478747B8A439616EC26F8C7891DCE","participant":"","addressingMode":"pn"},"messageTimestamp":1782012540},{"key":{"remoteJid":"2349122876837@s.whatsapp.net","fromMe":true,"id":"A50DA6B4CA86C5C2C1302D4831F258AC","participant":"","addressingMode":"pn"},"messageTimestamp":1782012563},{"key":{"remoteJid":"2349122876837@s.whatsapp.net","fromMe":true,"id":"A54C0B47ED1FBDD6894229E46D43F0E0","participant":"","addressingMode":"pn"},"messageTimestamp":1782012580},{"key":{"remoteJid":"2349122876837@s.whatsapp.net","fromMe":true,"id":"A51FB9F694B0CFD6D16D4B018E7B3CA7","participant":"","addressingMode":"pn"},"messageTimestamp":1782012606},{"key":{"remoteJid":"2349122876837@s.whatsapp.net","fromMe":true,"id":"A594E6BE27B125C18B38DEC12AF10985","participant":"","addressingMode":"pn"},"messageTimestamp":1782012642},{"key":{"remoteJid":"2349122876837@s.whatsapp.net","fromMe":true,"id":"A58A065B0540600752ED297D8EC67BDF","participant":"","addressingMode":"pn"},"messageTimestamp":1782012660},{"key":{"remoteJid":"2349122876837@s.whatsapp.net","fromMe":true,"id":"A557D84B348CBE6B459E29977C719A6C","participant":"","addressingMode":"pn"},"messageTimestamp":1782012671},{"key":{"remoteJid":"2349122876837@s.whatsapp.net","fromMe":true,"id":"A558589DF2A82A987D5AAA74055CD379","participant":"","addressingMode":"pn"},"messageTimestamp":1782012680},{"key":{"remoteJid":"2349122876837@s.whatsapp.net","fromMe":true,"id":"A5C90704A218C2B1D5AAFE6F496B5E95","participant":"","addressingMode":"pn"},"messageTimestamp":1782012681}],"nextPreKeyId":814,"firstUnuploadedPreKeyId":814,"accountSyncCounter":1,"accountSettings":{"unarchiveChats":false},"registered":true,"pairingCode":"K9TR1HJP","me":{"id":"2349122876837:8@s.whatsapp.net","name":"Arthur","lid":"148632242229491:8@lid"},"account":{"details":"CKKpjXkQ77Td0QYYASAAKAA=","accountSignatureKey":"eLzOi92feldIxPn1Tyond/MXjldcDCCKMxMQ7JUE4Vc=","accountSignature":"TuR1ZxQhnA27MyEaQlxZqlo49QozQ/09If9A2jprF3rrEmRBg3N8IRPG4Xlw40cgpqVdyaCYfGaj5+dkHbEmAw==","deviceSignature":"2y1d7OwB/+AF+U8+fdV6RF0H8ui2gGt8xf1xLscFffR9YjfohPROSDNGGNv/xNBkwn+Hhyl5EsXyUu/+uBhkBw=="},"signalIdentities":[{"identifier":{"name":"148632242229491:8@lid","deviceId":0},"identifierKey":{"type":"Buffer","data":"BXi8zovdn3pXSMT59U8qJ3fzF45XXAwgijMTEOyVBOFX"}}],"platform":"smba","routingInfo":{"type":"Buffer","data":"CAMICAgS"},"lastAccountSyncTimestamp":1782038303,"myAppStateKeyId":"AAAAAK/g","lastPropHash":"2dtLFI"}